optasoccer/__about__.py
optasoccer/__init__.py
optasoccer/metadata.py
optasoccer/parser.py
optasoccer-0.0.1.dist-info/METADATA
optasoccer-0.0.1.dist-info/WHEEL
optasoccer-0.0.1.dist-info/licenses/LICENSE
optasoccer-0.0.1.dist-info/RECORD
